redturtle.auditlog-1.0.0-py3.8-nspkg.pth
redturtle/auditlog/__init__.py
redturtle/auditlog/configure.zcml
redturtle/auditlog/interfaces.py
redturtle/auditlog/monkeys.py
redturtle/auditlog/subscribers.py
redturtle/auditlog/testing.py
redturtle/auditlog/locales/README.rst
redturtle/auditlog/locales/__init__.py
redturtle/auditlog/locales/redturtle.auditlog.pot
redturtle/auditlog/locales/update.py
redturtle/auditlog/locales/update.sh
redturtle/auditlog/locales/en/LC_MESSAGES/redturtle.auditlog.po
redturtle/auditlog/tests/__init__.py
redturtle/auditlog/tests/test_auditlog.py
redturtle.auditlog-1.0.0.dist-info/LICENSE.GPL
redturtle.auditlog-1.0.0.dist-info/LICENSE.rst
redturtle.auditlog-1.0.0.dist-info/METADATA
redturtle.auditlog-1.0.0.dist-info/WHEEL
redturtle.auditlog-1.0.0.dist-info/entry_points.txt
redturtle.auditlog-1.0.0.dist-info/namespace_packages.txt
redturtle.auditlog-1.0.0.dist-info/top_level.txt
redturtle.auditlog-1.0.0.dist-info/RECORD
